{
  "generated_from": "master_dataset.csv",
  "concepts": {
    "affordable_everyday_meal": {
      "description": "Affordable everyday dining",
      "primary_metric": "log_footfall",
      "criteria_used": [
        "log_footfall",
        "low_income_ratio",
        "mid_income_ratio",
        "hawker_stall_count_ratio",
        "mean_price_mid"
      ],
      "areas": [
        {
          "rank": 1,
          "planning_area": "WOODLANDS",
          "primary_metric": "log_footfall",
          "primary_value": 16.877,
          "primary_metric_display": {
            "key": "log_footfall",
            "label": "Total footfall",
            "value": 21356172,
            "formatted_value": "21,356,172",
            "unit": "visits"
          },
          "criteria_used": [
            "log_footfall",
            "low_income_ratio",
            "mid_income_ratio",
            "hawker_stall_count_ratio",
            "mean_price_mid"
          ],
          "criteria_display": [
            {
              "key": "log_footfall",
              "label": "Total footfall",
              "value": 21356172,
              "formatted_value": "21,356,172",
              "unit": "visits"
            },
            {
              "key": "low_income_ratio",
              "label": "Lower-income households",
              "value": 0.207,
              "formatted_value": "20.7%",
              "unit": "%"
            },
            {
              "key": "mid_income_ratio",
              "label": "Middle-income households",
              "value": 0.42,
              "formatted_value": "42.0%",
              "unit": "%"
            },
            {
              "key": "hawker_stall_count_ratio",
              "label": "Hawker presence",
              "value": 0.3883495145631068,
              "formatted_value": "38.8%",
              "unit": "%"
            },
            {
              "key": "mean_price_mid",
              "label": "Typical price level",
              "value": 9.172185430463577,
              "formatted_value": "9.17",
              "unit": "SGD"
            }
          ],
          "criteria_snapshot": "log_footfall=16.877; low_income_ratio=0.207; mid_income_ratio=0.420; hawker_stall_count_ratio=0.388; mean_price_mid=9.172",
          "kmeans_cluster": 0,
          "cluster_label": "Mainstream Urban / Heartland",
          "cluster_description": "supports stronger everyday demand, denser competition, and a more mass-market, affordable environment.",
          "cluster_assignment_method": "fit",
          "total_footfall": 21356172,
          "income_mix": {
            "low": 0.207,
            "mid": 0.42,
            "high": 0.374
          },
          "competitor_count": 206,
          "rent_proxy_psm": 131.97,
          "primary_demographic": "Mid-Age Adults",
          "primary_demographic_share": 0.304,
          "recommendation_summary": "This area is shortlisted for an affordable everyday dining and belongs to the Mainstream Urban / Heartland cluster, which supports stronger everyday demand, denser competition, and a more mass-market, affordable environment."
        },
        {
          "rank": 2,
          "planning_area": "BEDOK",
          "primary_metric": "log_footfall",
          "primary_value": 16.674,
          "primary_metric_display": {
            "key": "log_footfall",
            "label": "Total footfall",
            "value": 17435585,
            "formatted_value": "17,435,585",
            "unit": "visits"
          },
          "criteria_used": [
            "log_footfall",
            "low_income_ratio",
            "mid_income_ratio",
            "hawker_stall_count_ratio",
            "mean_price_mid"
          ],
          "criteria_display": [
            {
              "key": "log_footfall",
              "label": "Total footfall",
              "value": 17435585,
              "formatted_value": "17,435,585",
              "unit": "visits"
            },
            {
              "key": "low_income_ratio",
              "label": "Lower-income households",
              "value": 0.226,
              "formatted_value": "22.6%",
              "unit": "%"
            },
            {
              "key": "mid_income_ratio",
              "label": "Middle-income households",
              "value": 0.309,
              "formatted_value": "30.9%",
              "unit": "%"
            },
            {
              "key": "hawker_stall_count_ratio",
              "label": "Hawker presence",
              "value": 0.16136919315403422,
              "formatted_value": "16.1%",
              "unit": "%"
            },
            {
              "key": "mean_price_mid",
              "label": "Typical price level",
              "value": 13.389705882352942,
              "formatted_value": "13.39",
              "unit": "SGD"
            }
          ],
          "criteria_snapshot": "log_footfall=16.674; low_income_ratio=0.226; mid_income_ratio=0.309; hawker_stall_count_ratio=0.161; mean_price_mid=13.390",
          "kmeans_cluster": 0,
          "cluster_label": "Mainstream Urban / Heartland",
          "cluster_description": "supports stronger everyday demand, denser competition, and a more mass-market, affordable environment.",
          "cluster_assignment_method": "fit",
          "total_footfall": 17435585,
          "income_mix": {
            "low": 0.226,
            "mid": 0.309,
            "high": 0.465
          },
          "competitor_count": 409,
          "rent_proxy_psm": 226.14,
          "primary_demographic": "Mid-Age Adults",
          "primary_demographic_share": 0.283,
          "recommendation_summary": "This area is shortlisted for an affordable everyday dining and belongs to the Mainstream Urban / Heartland cluster, which supports stronger everyday demand, denser competition, and a more mass-market, affordable environment."
        },
        {
          "rank": 3,
          "planning_area": "BUKIT MERAH",
          "primary_metric": "log_footfall",
          "primary_value": 16.612,
          "primary_metric_display": {
            "key": "log_footfall",
            "label": "Total footfall",
            "value": 16390155,
            "formatted_value": "16,390,155",
            "unit": "visits"
          },
          "criteria_used": [
            "log_footfall",
            "low_income_ratio",
            "mid_income_ratio",
            "hawker_stall_count_ratio",
            "mean_price_mid"
          ],
          "criteria_display": [
            {
              "key": "log_footfall",
              "label": "Total footfall",
              "value": 16390155,
              "formatted_value": "16,390,155",
              "unit": "visits"
            },
            {
              "key": "low_income_ratio",
              "label": "Lower-income households",
              "value": 0.284,
              "formatted_value": "28.4%",
              "unit": "%"
            },
            {
              "key": "mid_income_ratio",
              "label": "Middle-income households",
              "value": 0.274,
              "formatted_value": "27.4%",
              "unit": "%"
            },
            {
              "key": "hawker_stall_count_ratio",
              "label": "Hawker presence",
              "value": 0.3945409429280397,
              "formatted_value": "39.5%",
              "unit": "%"
            },
            {
              "key": "mean_price_mid",
              "label": "Typical price level",
              "value": 13.53573883161512,
              "formatted_value": "13.54",
              "unit": "SGD"
            }
          ],
          "criteria_snapshot": "log_footfall=16.612; low_income_ratio=0.284; mid_income_ratio=0.274; hawker_stall_count_ratio=0.395; mean_price_mid=13.536",
          "kmeans_cluster": 0,
          "cluster_label": "Mainstream Urban / Heartland",
          "cluster_description": "supports stronger everyday demand, denser competition, and a more mass-market, affordable environment.",
          "cluster_assignment_method": "fit",
          "total_footfall": 16390155,
          "income_mix": {
            "low": 0.284,
            "mid": 0.274,
            "high": 0.442
          },
          "competitor_count": 403,
          "rent_proxy_psm": 286.56,
          "primary_demographic": "Mid-Age Adults",
          "primary_demographic_share": 0.297,
          "recommendation_summary": "This area is shortlisted for an affordable everyday dining and belongs to the Mainstream Urban / Heartland cluster, which supports stronger everyday demand, denser competition, and a more mass-market, affordable environment."
        },
        {
          "rank": 4,
          "planning_area": "GEYLANG",
          "primary_metric": "log_footfall",
          "primary_value": 16.496,
          "primary_metric_display": {
            "key": "log_footfall",
            "label": "Total footfall",
            "value": 14594907,
            "formatted_value": "14,594,907",
            "unit": "visits"
          },
          "criteria_used": [
            "log_footfall",
            "low_income_ratio",
            "mid_income_ratio",
            "hawker_stall_count_ratio",
            "mean_price_mid"
          ],
          "criteria_display": [
            {
              "key": "log_footfall",
              "label": "Total footfall",
              "value": 14594907,
              "formatted_value": "14,594,907",
              "unit": "visits"
            },
            {
              "key": "low_income_ratio",
              "label": "Lower-income households",
              "value": 0.267,
              "formatted_value": "26.7%",
              "unit": "%"
            },
            {
              "key": "mid_income_ratio",
              "label": "Middle-income households",
              "value": 0.337,
              "formatted_value": "33.7%",
              "unit": "%"
            },
            {
              "key": "hawker_stall_count_ratio",
              "label": "Hawker presence",
              "value": 0.22268041237113403,
              "formatted_value": "22.3%",
              "unit": "%"
            },
            {
              "key": "mean_price_mid",
              "label": "Typical price level",
              "value": 13.367924528301886,
              "formatted_value": "13.37",
              "unit": "SGD"
            }
          ],
          "criteria_snapshot": "log_footfall=16.496; low_income_ratio=0.267; mid_income_ratio=0.337; hawker_stall_count_ratio=0.223; mean_price_mid=13.368",
          "kmeans_cluster": 0,
          "cluster_label": "Mainstream Urban / Heartland",
          "cluster_description": "supports stronger everyday demand, denser competition, and a more mass-market, affordable environment.",
          "cluster_assignment_method": "fit",
          "total_footfall": 14594907,
          "income_mix": {
            "low": 0.267,
            "mid": 0.337,
            "high": 0.396
          },
          "competitor_count": 485,
          "rent_proxy_psm": 128.86,
          "primary_demographic": "Mid-Age Adults",
          "primary_demographic_share": 0.288,
          "recommendation_summary": "This area is shortlisted for an affordable everyday dining and belongs to the Mainstream Urban / Heartland cluster, which supports stronger everyday demand, denser competition, and a more mass-market, affordable environment."
        },
        {
          "rank": 5,
          "planning_area": "YISHUN",
          "primary_metric": "log_footfall",
          "primary_value": 16.476,
          "primary_metric_display": {
            "key": "log_footfall",
            "label": "Total footfall",
            "value": 14304556,
            "formatted_value": "14,304,556",
            "unit": "visits"
          },
          "criteria_used": [
            "log_footfall",
            "low_income_ratio",
            "mid_income_ratio",
            "hawker_stall_count_ratio",
            "mean_price_mid"
          ],
          "criteria_display": [
            {
              "key": "log_footfall",
              "label": "Total footfall",
              "value": 14304556,
              "formatted_value": "14,304,556",
              "unit": "visits"
            },
            {
              "key": "low_income_ratio",
              "label": "Lower-income households",
              "value": 0.237,
              "formatted_value": "23.7%",
              "unit": "%"
            },
            {
              "key": "mid_income_ratio",
              "label": "Middle-income households",
              "value": 0.395,
              "formatted_value": "39.5%",
              "unit": "%"
            },
            {
              "key": "hawker_stall_count_ratio",
              "label": "Hawker presence",
              "value": 0.1566265060240964,
              "formatted_value": "15.7%",
              "unit": "%"
            },
            {
              "key": "mean_price_mid",
              "label": "Typical price level",
              "value": 12.365079365079366,
              "formatted_value": "12.37",
              "unit": "SGD"
            }
          ],
          "criteria_snapshot": "log_footfall=16.476; low_income_ratio=0.237; mid_income_ratio=0.395; hawker_stall_count_ratio=0.157; mean_price_mid=12.365",
          "kmeans_cluster": 0,
          "cluster_label": "Mainstream Urban / Heartland",
          "cluster_description": "supports stronger everyday demand, denser competition, and a more mass-market, affordable environment.",
          "cluster_assignment_method": "fit",
          "total_footfall": 14304556,
          "income_mix": {
            "low": 0.237,
            "mid": 0.395,
            "high": 0.368
          },
          "competitor_count": 166,
          "rent_proxy_psm": 97.14,
          "primary_demographic": "Mid-Age Adults",
          "primary_demographic_share": 0.295,
          "recommendation_summary": "This area is shortlisted for an affordable everyday dining and belongs to the Mainstream Urban / Heartland cluster, which supports stronger everyday demand, denser competition, and a more mass-market, affordable environment."
        }
      ]
    },
    "premium_cafe": {
      "description": "Premium cafe / specialty cafe",
      "primary_metric": "mean_price_mid",
      "criteria_used": [
        "mean_price_mid",
        "high_income_ratio",
        "unique_category_count",
        "mean_rating"
      ],
      "areas": [
        {
          "rank": 1,
          "planning_area": "TANGLIN",
          "primary_metric": "mean_price_mid",
          "primary_value": 50.667,
          "primary_metric_display": {
            "key": "mean_price_mid",
            "label": "Typical price level",
            "value": 50.666666666666664,
            "formatted_value": "50.67",
            "unit": "SGD"
          },
          "criteria_used": [
            "mean_price_mid",
            "high_income_ratio",
            "unique_category_count",
            "mean_rating"
          ],
          "criteria_display": [
            {
              "key": "mean_price_mid",
              "label": "Typical price level",
              "value": 50.666666666666664,
              "formatted_value": "50.67",
              "unit": "SGD"
            },
            {
              "key": "high_income_ratio",
              "label": "Higher-income households",
              "value": 0.81,
              "formatted_value": "81.0%",
              "unit": "%"
            },
            {
              "key": "unique_category_count",
              "label": "Category diversity",
              "value": 36,
              "formatted_value": "36",
              "unit": "count"
            },
            {
              "key": "mean_rating",
              "label": "Average rating",
              "value": 4.357352941176471,
              "formatted_value": "4.36/5",
              "unit": "/5"
            }
          ],
          "criteria_snapshot": "mean_price_mid=50.667; high_income_ratio=0.810; unique_category_count=36.000; mean_rating=4.357",
          "kmeans_cluster": 2,
          "cluster_label": "Premium Central / Lifestyle",
          "cluster_description": "supports higher price points, stronger ratings, and greater category diversity.",
          "cluster_assignment_method": "fit",
          "total_footfall": 2359005,
          "income_mix": {
            "low": 0.058,
            "mid": 0.132,
            "high": 0.81
          },
          "competitor_count": 68,
          "rent_proxy_psm": 42.59,
          "primary_demographic": "Mid-Age Adults",
          "primary_demographic_share": 0.347,
          "recommendation_summary": "This area is shortlisted for a premium cafe / specialty cafe and belongs to the Premium Central / Lifestyle cluster, which supports higher price points, stronger ratings, and greater category diversity."
        },
        {
          "rank": 2,
          "planning_area": "RIVER VALLEY",
          "primary_metric": "mean_price_mid",
          "primary_value": 48.559,
          "primary_metric_display": {
            "key": "mean_price_mid",
            "label": "Typical price level",
            "value": 48.55882352941177,
            "formatted_value": "48.56",
            "unit": "SGD"
          },
          "criteria_used": [
            "mean_price_mid",
            "high_income_ratio",
            "unique_category_count",
            "mean_rating"
          ],
          "criteria_display": [
            {
              "key": "mean_price_mid",
              "label": "Typical price level",
              "value": 48.55882352941177,
              "formatted_value": "48.56",
              "unit": "SGD"
            },
            {
              "key": "high_income_ratio",
              "label": "Higher-income households",
              "value": 0.776,
              "formatted_value": "77.6%",
              "unit": "%"
            },
            {
              "key": "unique_category_count",
              "label": "Category diversity",
              "value": 21,
              "formatted_value": "21",
              "unit": "count"
            },
            {
              "key": "mean_rating",
              "label": "Average rating",
              "value": 4.462962962962963,
              "formatted_value": "4.46/5",
              "unit": "/5"
            }
          ],
          "criteria_snapshot": "mean_price_mid=48.559; high_income_ratio=0.776; unique_category_count=21.000; mean_rating=4.463",
          "kmeans_cluster": 2,
          "cluster_label": "Premium Central / Lifestyle",
          "cluster_description": "supports higher price points, stronger ratings, and greater category diversity.",
          "cluster_assignment_method": "fit",
          "total_footfall": 328637,
          "income_mix": {
            "low": 0.083,
            "mid": 0.14,
            "high": 0.776
          },
          "competitor_count": 27,
          "rent_proxy_psm": 44.24,
          "primary_demographic": "Mid-Age Adults",
          "primary_demographic_share": 0.384,
          "recommendation_summary": "This area is shortlisted for a premium cafe / specialty cafe and belongs to the Premium Central / Lifestyle cluster, which supports higher price points, stronger ratings, and greater category diversity."
        },
        {
          "rank": 3,
          "planning_area": "OUTRAM",
          "primary_metric": "mean_price_mid",
          "primary_value": 42.372,
          "primary_metric_display": {
            "key": "mean_price_mid",
            "label": "Typical price level",
            "value": 42.37150837988827,
            "formatted_value": "42.37",
            "unit": "SGD"
          },
          "criteria_used": [
            "mean_price_mid",
            "high_income_ratio",
            "unique_category_count",
            "mean_rating"
          ],
          "criteria_display": [
            {
              "key": "mean_price_mid",
              "label": "Typical price level",
              "value": 42.37150837988827,
              "formatted_value": "42.37",
              "unit": "SGD"
            },
            {
              "key": "high_income_ratio",
              "label": "Higher-income households",
              "value": 0.387,
              "formatted_value": "38.7%",
              "unit": "%"
            },
            {
              "key": "unique_category_count",
              "label": "Category diversity",
              "value": 76,
              "formatted_value": "76",
              "unit": "count"
            },
            {
              "key": "mean_rating",
              "label": "Average rating",
              "value": 4.459442724458205,
              "formatted_value": "4.46/5",
              "unit": "/5"
            }
          ],
          "criteria_snapshot": "mean_price_mid=42.372; high_income_ratio=0.387; unique_category_count=76.000; mean_rating=4.459",
          "kmeans_cluster": 2,
          "cluster_label": "Premium Central / Lifestyle",
          "cluster_description": "supports higher price points, stronger ratings, and greater category diversity.",
          "cluster_assignment_method": "fit",
          "total_footfall": 4332449,
          "income_mix": {
            "low": 0.359,
            "mid": 0.254,
            "high": 0.387
          },
          "competitor_count": 323,
          "rent_proxy_psm": 60.02,
          "primary_demographic": "Mid-Age Adults",
          "primary_demographic_share": 0.295,
          "recommendation_summary": "This area is shortlisted for a premium cafe / specialty cafe and belongs to the Premium Central / Lifestyle cluster, which supports higher price points, stronger ratings, and greater category diversity."
        },
        {
          "rank": 4,
          "planning_area": "DOWNTOWN CORE",
          "primary_metric": "mean_price_mid",
          "primary_value": 33.6,
          "primary_metric_display": {
            "key": "mean_price_mid",
            "label": "Typical price level",
            "value": 33.6,
            "formatted_value": "33.60",
            "unit": "SGD"
          },
          "criteria_used": [
            "mean_price_mid",
            "high_income_ratio",
            "unique_category_count",
            "mean_rating"
          ],
          "criteria_display": [
            {
              "key": "mean_price_mid",
              "label": "Typical price level",
              "value": 33.6,
              "formatted_value": "33.60",
              "unit": "SGD"
            },
            {
              "key": "high_income_ratio",
              "label": "Higher-income households",
              "value": 0.74,
              "formatted_value": "74.0%",
              "unit": "%"
            },
            {
              "key": "unique_category_count",
              "label": "Category diversity",
              "value": 117,
              "formatted_value": "117",
              "unit": "count"
            },
            {
              "key": "mean_rating",
              "label": "Average rating",
              "value": 4.308620689655172,
              "formatted_value": "4.31/5",
              "unit": "/5"
            }
          ],
          "criteria_snapshot": "mean_price_mid=33.600; high_income_ratio=0.740; unique_category_count=117.000; mean_rating=4.309",
          "kmeans_cluster": 2,
          "cluster_label": "Premium Central / Lifestyle",
          "cluster_description": "supports higher price points, stronger ratings, and greater category diversity.",
          "cluster_assignment_method": "fit",
          "total_footfall": 15722045,
          "income_mix": {
            "low": 0.073,
            "mid": 0.187,
            "high": 0.74
          },
          "competitor_count": 760,
          "rent_proxy_psm": 211.15,
          "primary_demographic": "Mid-Age Adults",
          "primary_demographic_share": 0.407,
          "recommendation_summary": "This area is shortlisted for a premium cafe / specialty cafe and belongs to the Premium Central / Lifestyle cluster, which supports higher price points, stronger ratings, and greater category diversity."
        },
        {
          "rank": 5,
          "planning_area": "BUKIT TIMAH",
          "primary_metric": "mean_price_mid",
          "primary_value": 15.242,
          "primary_metric_display": {
            "key": "mean_price_mid",
            "label": "Typical price level",
            "value": 15.242307692307692,
            "formatted_value": "15.24",
            "unit": "SGD"
          },
          "criteria_used": [
            "mean_price_mid",
            "high_income_ratio",
            "unique_category_count",
            "mean_rating"
          ],
          "criteria_display": [
            {
              "key": "mean_price_mid",
              "label": "Typical price level",
              "value": 15.242307692307692,
              "formatted_value": "15.24",
              "unit": "SGD"
            },
            {
              "key": "high_income_ratio",
              "label": "Higher-income households",
              "value": 0.775,
              "formatted_value": "77.5%",
              "unit": "%"
            },
            {
              "key": "unique_category_count",
              "label": "Category diversity",
              "value": 54,
              "formatted_value": "54",
              "unit": "count"
            },
            {
              "key": "mean_rating",
              "label": "Average rating",
              "value": 4.298314606741573,
              "formatted_value": "4.30/5",
              "unit": "/5"
            }
          ],
          "criteria_snapshot": "mean_price_mid=15.242; high_income_ratio=0.775; unique_category_count=54.000; mean_rating=4.298",
          "kmeans_cluster": 0,
          "cluster_label": "Mainstream Urban / Heartland",
          "cluster_description": "supports stronger everyday demand, denser competition, and a more mass-market, affordable environment.",
          "cluster_assignment_method": "fit",
          "total_footfall": 6448367,
          "income_mix": {
            "low": 0.071,
            "mid": 0.154,
            "high": 0.775
          },
          "competitor_count": 180,
          "rent_proxy_psm": 102.65,
          "primary_demographic": "Mid-Age Adults",
          "primary_demographic_share": 0.3,
          "recommendation_summary": "This area is shortlisted for a premium cafe / specialty cafe and belongs to the Mainstream Urban / Heartland cluster, which supports stronger everyday demand, denser competition, and a more mass-market, affordable environment."
        }
      ]
    },
    "family_casual_dining": {
      "description": "Family-oriented casual dining",
      "primary_metric": "mid_income_ratio",
      "criteria_used": [
        "children_ratio",
        "mid_age_adults_ratio",
        "weekend_ratio",
        "mid_income_ratio",
        "mean_price_mid",
        "log_competitor_count"
      ],
      "areas": [
        {
          "rank": 1,
          "planning_area": "WOODLANDS",
          "primary_metric": "mid_income_ratio",
          "primary_value": 0.42,
          "primary_metric_display": {
            "key": "mid_income_ratio",
            "label": "Middle-income households",
            "value": 0.42,
            "formatted_value": "42.0%",
            "unit": "%"
          },
          "criteria_used": [
            "children_ratio",
            "mid_age_adults_ratio",
            "weekend_ratio",
            "mid_income_ratio",
            "mean_price_mid",
            "log_competitor_count"
          ],
          "criteria_display": [
            {
              "key": "children_ratio",
              "label": "Families with children",
              "value": 0.15082506957237488,
              "formatted_value": "15.1%",
              "unit": "%"
            },
            {
              "key": "mid_age_adults_ratio",
              "label": "Mid-age adults",
              "value": 0.30368831576059263,
              "formatted_value": "30.4%",
              "unit": "%"
            },
            {
              "key": "weekend_ratio",
              "label": "Weekend activity share",
              "value": 0.2991065065405916,
              "formatted_value": "29.9%",
              "unit": "%"
            },
            {
              "key": "mid_income_ratio",
              "label": "Middle-income households",
              "value": 0.42,
              "formatted_value": "42.0%",
              "unit": "%"
            },
            {
              "key": "mean_price_mid",
              "label": "Typical price level",
              "value": 9.172185430463577,
              "formatted_value": "9.17",
              "unit": "SGD"
            },
            {
              "key": "log_competitor_count",
              "label": "Nearby competitors",
              "value": 206,
              "formatted_value": "206",
              "unit": "competitors"
            }
          ],
          "criteria_snapshot": "children_ratio=0.151; mid_age_adults_ratio=0.304; weekend_ratio=0.299; mid_income_ratio=0.420; mean_price_mid=9.172; log_competitor_count=5.333",
          "kmeans_cluster": 0,
          "cluster_label": "Mainstream Urban / Heartland",
          "cluster_description": "supports stronger everyday demand, denser competition, and a more mass-market, affordable environment.",
          "cluster_assignment_method": "fit",
          "total_footfall": 21356172,
          "income_mix": {
            "low": 0.207,
            "mid": 0.42,
            "high": 0.374
          },
          "competitor_count": 206,
          "rent_proxy_psm": 131.97,
          "primary_demographic": "Mid-Age Adults",
          "primary_demographic_share": 0.304,
          "recommendation_summary": "This area is shortlisted for a family-oriented casual dining and belongs to the Mainstream Urban / Heartland cluster, which supports stronger everyday demand, denser competition, and a more mass-market, affordable environment."
        },
        {
          "rank": 2,
          "planning_area": "JURONG WEST",
          "primary_metric": "mid_income_ratio",
          "primary_value": 0.395,
          "primary_metric_display": {
            "key": "mid_income_ratio",
            "label": "Middle-income households",
            "value": 0.395,
            "formatted_value": "39.5%",
            "unit": "%"
          },
          "criteria_used": [
            "children_ratio",
            "mid_age_adults_ratio",
            "weekend_ratio",
            "mid_income_ratio",
            "mean_price_mid",
            "log_competitor_count"
          ],
          "criteria_display": [
            {
              "key": "children_ratio",
              "label": "Families with children",
              "value": 0.14681588062883028,
              "formatted_value": "14.7%",
              "unit": "%"
            },
            {
              "key": "mid_age_adults_ratio",
              "label": "Mid-age adults",
              "value": 0.3125118952457082,
              "formatted_value": "31.3%",
              "unit": "%"
            },
            {
              "key": "weekend_ratio",
              "label": "Weekend activity share",
              "value": 0.2910712975175303,
              "formatted_value": "29.1%",
              "unit": "%"
            },
            {
              "key": "mid_income_ratio",
              "label": "Middle-income households",
              "value": 0.395,
              "formatted_value": "39.5%",
              "unit": "%"
            },
            {
              "key": "mean_price_mid",
              "label": "Typical price level",
              "value": 10.71439393939394,
              "formatted_value": "10.71",
              "unit": "SGD"
            },
            {
              "key": "log_competitor_count",
              "label": "Nearby competitors",
              "value": 186,
              "formatted_value": "186",
              "unit": "competitors"
            }
          ],
          "criteria_snapshot": "children_ratio=0.147; mid_age_adults_ratio=0.313; weekend_ratio=0.291; mid_income_ratio=0.395; mean_price_mid=10.714; log_competitor_count=5.231",
          "kmeans_cluster": 0,
          "cluster_label": "Mainstream Urban / Heartland",
          "cluster_description": "supports stronger everyday demand, denser competition, and a more mass-market, affordable environment.",
          "cluster_assignment_method": "fit",
          "total_footfall": 18176818,
          "income_mix": {
            "low": 0.192,
            "mid": 0.395,
            "high": 0.413
          },
          "competitor_count": 186,
          "rent_proxy_psm": 154.04,
          "primary_demographic": "Mid-Age Adults",
          "primary_demographic_share": 0.313,
          "recommendation_summary": "This area is shortlisted for a family-oriented casual dining and belongs to the Mainstream Urban / Heartland cluster, which supports stronger everyday demand, denser competition, and a more mass-market, affordable environment."
        },
        {
          "rank": 3,
          "planning_area": "YISHUN",
          "primary_metric": "mid_income_ratio",
          "primary_value": 0.395,
          "primary_metric_display": {
            "key": "mid_income_ratio",
            "label": "Middle-income households",
            "value": 0.395,
            "formatted_value": "39.5%",
            "unit": "%"
          },
          "criteria_used": [
            "children_ratio",
            "mid_age_adults_ratio",
            "weekend_ratio",
            "mid_income_ratio",
            "mean_price_mid",
            "log_competitor_count"
          ],
          "criteria_display": [
            {
              "key": "children_ratio",
              "label": "Families with children",
              "value": 0.15390861112364113,
              "formatted_value": "15.4%",
              "unit": "%"
            },
            {
              "key": "mid_age_adults_ratio",
              "label": "Mid-age adults",
              "value": 0.2945554603274843,
              "formatted_value": "29.5%",
              "unit": "%"
            },
            {
              "key": "weekend_ratio",
              "label": "Weekend activity share",
              "value": 0.2970587133218256,
              "formatted_value": "29.7%",
              "unit": "%"
            },
            {
              "key": "mid_income_ratio",
              "label": "Middle-income households",
              "value": 0.395,
              "formatted_value": "39.5%",
              "unit": "%"
            },
            {
              "key": "mean_price_mid",
              "label": "Typical price level",
              "value": 12.365079365079366,
              "formatted_value": "12.37",
              "unit": "SGD"
            },
            {
              "key": "log_competitor_count",
              "label": "Nearby competitors",
              "value": 166,
              "formatted_value": "166",
              "unit": "competitors"
            }
          ],
          "criteria_snapshot": "children_ratio=0.154; mid_age_adults_ratio=0.295; weekend_ratio=0.297; mid_income_ratio=0.395; mean_price_mid=12.365; log_competitor_count=5.118",
          "kmeans_cluster": 0,
          "cluster_label": "Mainstream Urban / Heartland",
          "cluster_description": "supports stronger everyday demand, denser competition, and a more mass-market, affordable environment.",
          "cluster_assignment_method": "fit",
          "total_footfall": 14304556,
          "income_mix": {
            "low": 0.237,
            "mid": 0.395,
            "high": 0.368
          },
          "competitor_count": 166,
          "rent_proxy_psm": 97.14,
          "primary_demographic": "Mid-Age Adults",
          "primary_demographic_share": 0.295,
          "recommendation_summary": "This area is shortlisted for a family-oriented casual dining and belongs to the Mainstream Urban / Heartland cluster, which supports stronger everyday demand, denser competition, and a more mass-market, affordable environment."
        },
        {
          "rank": 4,
          "planning_area": "SEMBAWANG",
          "primary_metric": "mid_income_ratio",
          "primary_value": 0.382,
          "primary_metric_display": {
            "key": "mid_income_ratio",
            "label": "Middle-income households",
            "value": 0.382,
            "formatted_value": "38.2%",
            "unit": "%"
          },
          "criteria_used": [
            "children_ratio",
            "mid_age_adults_ratio",
            "weekend_ratio",
            "mid_income_ratio",
            "mean_price_mid",
            "log_competitor_count"
          ],
          "criteria_display": [
            {
              "key": "children_ratio",
              "label": "Families with children",
              "value": 0.18039330218068536,
              "formatted_value": "18.0%",
              "unit": "%"
            },
            {
              "key": "mid_age_adults_ratio",
              "label": "Mid-age adults",
              "value": 0.3257398753894081,
              "formatted_value": "32.6%",
              "unit": "%"
            },
            {
              "key": "weekend_ratio",
              "label": "Weekend activity share",
              "value": 0.2917036871132704,
              "formatted_value": "29.2%",
              "unit": "%"
            },
            {
              "key": "mid_income_ratio",
              "label": "Middle-income households",
              "value": 0.382,
              "formatted_value": "38.2%",
              "unit": "%"
            },
            {
              "key": "mean_price_mid",
              "label": "Typical price level",
              "value": 11.301282051282053,
              "formatted_value": "11.30",
              "unit": "SGD"
            },
            {
              "key": "log_competitor_count",
              "label": "Nearby competitors",
              "value": 112,
              "formatted_value": "112",
              "unit": "competitors"
            }
          ],
          "criteria_snapshot": "children_ratio=0.180; mid_age_adults_ratio=0.326; weekend_ratio=0.292; mid_income_ratio=0.382; mean_price_mid=11.301; log_competitor_count=4.727",
          "kmeans_cluster": 0,
          "cluster_label": "Mainstream Urban / Heartland",
          "cluster_description": "supports stronger everyday demand, denser competition, and a more mass-market, affordable environment.",
          "cluster_assignment_method": "fit",
          "total_footfall": 7304522,
          "income_mix": {
            "low": 0.189,
            "mid": 0.382,
            "high": 0.429
          },
          "competitor_count": 112,
          "rent_proxy_psm": 97.14,
          "primary_demographic": "Mid-Age Adults",
          "primary_demographic_share": 0.326,
          "recommendation_summary": "This area is shortlisted for a family-oriented casual dining and belongs to the Mainstream Urban / Heartland cluster, which supports stronger everyday demand, denser competition, and a more mass-market, affordable environment."
        },
        {
          "rank": 5,
          "planning_area": "JURONG EAST",
          "primary_metric": "mid_income_ratio",
          "primary_value": 0.378,
          "primary_metric_display": {
            "key": "mid_income_ratio",
            "label": "Middle-income households",
            "value": 0.378,
            "formatted_value": "37.8%",
            "unit": "%"
          },
          "criteria_used": [
            "children_ratio",
            "mid_age_adults_ratio",
            "weekend_ratio",
            "mid_income_ratio",
            "mean_price_mid",
            "log_competitor_count"
          ],
          "criteria_display": [
            {
              "key": "children_ratio",
              "label": "Families with children",
              "value": 0.1138387178834902,
              "formatted_value": "11.4%",
              "unit": "%"
            },
            {
              "key": "mid_age_adults_ratio",
              "label": "Mid-age adults",
              "value": 0.2774103281607733,
              "formatted_value": "27.7%",
              "unit": "%"
            },
            {
              "key": "weekend_ratio",
              "label": "Weekend activity share",
              "value": 0.3141716107845781,
              "formatted_value": "31.4%",
              "unit": "%"
            },
            {
              "key": "mid_income_ratio",
              "label": "Middle-income households",
              "value": 0.378,
              "formatted_value": "37.8%",
              "unit": "%"
            },
            {
              "key": "mean_price_mid",
              "label": "Typical price level",
              "value": 13.871428571428572,
              "formatted_value": "13.87",
              "unit": "SGD"
            },
            {
              "key": "log_competitor_count",
              "label": "Nearby competitors",
              "value": 185,
              "formatted_value": "185",
              "unit": "competitors"
            }
          ],
          "criteria_snapshot": "children_ratio=0.114; mid_age_adults_ratio=0.277; weekend_ratio=0.314; mid_income_ratio=0.378; mean_price_mid=13.871; log_competitor_count=5.226",
          "kmeans_cluster": 0,
          "cluster_label": "Mainstream Urban / Heartland",
          "cluster_description": "supports stronger everyday demand, denser competition, and a more mass-market, affordable environment.",
          "cluster_assignment_method": "fit",
          "total_footfall": 9792613,
          "income_mix": {
            "low": 0.229,
            "mid": 0.378,
            "high": 0.392
          },
          "competitor_count": 185,
          "rent_proxy_psm": 116.36,
          "primary_demographic": "Mid-Age Adults",
          "primary_demographic_share": 0.277,
          "recommendation_summary": "This area is shortlisted for a family-oriented casual dining and belongs to the Mainstream Urban / Heartland cluster, which supports stronger everyday demand, denser competition, and a more mass-market, affordable environment."
        }
      ]
    },
    "local_cuisine": {
      "description": "Local cuisine / traditional favorites",
      "primary_metric": "hawker_stall_count_ratio",
      "criteria_used": [
        "chinese_count_ratio",
        "indian_count_ratio",
        "hawker_stall_count_ratio",
        "cafe_count_ratio"
      ],
      "areas": [
        {
          "rank": 1,
          "planning_area": "NEWTON",
          "primary_metric": "hawker_stall_count_ratio",
          "primary_value": 0.549,
          "primary_metric_display": {
            "key": "hawker_stall_count_ratio",
            "label": "Hawker presence",
            "value": 0.5490196078431373,
            "formatted_value": "54.9%",
            "unit": "%"
          },
          "criteria_used": [
            "chinese_count_ratio",
            "indian_count_ratio",
            "hawker_stall_count_ratio",
            "cafe_count_ratio"
          ],
          "criteria_display": [
            {
              "key": "chinese_count_ratio",
              "label": "Chinese cuisine presence",
              "value": 0.0196078431372549,
              "formatted_value": "2.0%",
              "unit": "%"
            },
            {
              "key": "indian_count_ratio",
              "label": "Indian cuisine presence",
              "value": 0.0196078431372549,
              "formatted_value": "2.0%",
              "unit": "%"
            },
            {
              "key": "hawker_stall_count_ratio",
              "label": "Hawker presence",
              "value": 0.5490196078431373,
              "formatted_value": "54.9%",
              "unit": "%"
            },
            {
              "key": "cafe_count_ratio",
              "label": "Cafe presence",
              "value": 0.0,
              "formatted_value": "0.0%",
              "unit": "%"
            }
          ],
          "criteria_snapshot": "chinese_count_ratio=0.020; indian_count_ratio=0.020; hawker_stall_count_ratio=0.549; cafe_count_ratio=0.000",
          "kmeans_cluster": 0,
          "cluster_label": "Mainstream Urban / Heartland",
          "cluster_description": "supports stronger everyday demand, denser competition, and a more mass-market, affordable environment.",
          "cluster_assignment_method": "fit",
          "total_footfall": 3535836,
          "income_mix": {
            "low": null,
            "mid": null,
            "high": null
          },
          "competitor_count": 51,
          "rent_proxy_psm": 44.24,
          "primary_demographic": "Mid-Age Adults",
          "primary_demographic_share": 0.352,
          "recommendation_summary": "This area is shortlisted for a local cuisine / traditional favorites and belongs to the Mainstream Urban / Heartland cluster, which supports stronger everyday demand, denser competition, and a more mass-market, affordable environment."
        },
        {
          "rank": 2,
          "planning_area": "BUKIT MERAH",
          "primary_metric": "hawker_stall_count_ratio",
          "primary_value": 0.395,
          "primary_metric_display": {
            "key": "hawker_stall_count_ratio",
            "label": "Hawker presence",
            "value": 0.3945409429280397,
            "formatted_value": "39.5%",
            "unit": "%"
          },
          "criteria_used": [
            "chinese_count_ratio",
            "indian_count_ratio",
            "hawker_stall_count_ratio",
            "cafe_count_ratio"
          ],
          "criteria_display": [
            {
              "key": "chinese_count_ratio",
              "label": "Chinese cuisine presence",
              "value": 0.05459057071960298,
              "formatted_value": "5.5%",
              "unit": "%"
            },
            {
              "key": "indian_count_ratio",
              "label": "Indian cuisine presence",
              "value": 0.007444168734491315,
              "formatted_value": "0.7%",
              "unit": "%"
            },
            {
              "key": "hawker_stall_count_ratio",
              "label": "Hawker presence",
              "value": 0.3945409429280397,
              "formatted_value": "39.5%",
              "unit": "%"
            },
            {
              "key": "cafe_count_ratio",
              "label": "Cafe presence",
              "value": 0.03225806451612903,
              "formatted_value": "3.2%",
              "unit": "%"
            }
          ],
          "criteria_snapshot": "chinese_count_ratio=0.055; indian_count_ratio=0.007; hawker_stall_count_ratio=0.395; cafe_count_ratio=0.032",
          "kmeans_cluster": 0,
          "cluster_label": "Mainstream Urban / Heartland",
          "cluster_description": "supports stronger everyday demand, denser competition, and a more mass-market, affordable environment.",
          "cluster_assignment_method": "fit",
          "total_footfall": 16390155,
          "income_mix": {
            "low": 0.284,
            "mid": 0.274,
            "high": 0.442
          },
          "competitor_count": 403,
          "rent_proxy_psm": 286.56,
          "primary_demographic": "Mid-Age Adults",
          "primary_demographic_share": 0.297,
          "recommendation_summary": "This area is shortlisted for a local cuisine / traditional favorites and belongs to the Mainstream Urban / Heartland cluster, which supports stronger everyday demand, denser competition, and a more mass-market, affordable environment."
        },
        {
          "rank": 3,
          "planning_area": "WOODLANDS",
          "primary_metric": "hawker_stall_count_ratio",
          "primary_value": 0.388,
          "primary_metric_display": {
            "key": "hawker_stall_count_ratio",
            "label": "Hawker presence",
            "value": 0.3883495145631068,
            "formatted_value": "38.8%",
            "unit": "%"
          },
          "criteria_used": [
            "chinese_count_ratio",
            "indian_count_ratio",
            "hawker_stall_count_ratio",
            "cafe_count_ratio"
          ],
          "criteria_display": [
            {
              "key": "chinese_count_ratio",
              "label": "Chinese cuisine presence",
              "value": 0.02912621359223301,
              "formatted_value": "2.9%",
              "unit": "%"
            },
            {
              "key": "indian_count_ratio",
              "label": "Indian cuisine presence",
              "value": 0.019417475728155338,
              "formatted_value": "1.9%",
              "unit": "%"
            },
            {
              "key": "hawker_stall_count_ratio",
              "label": "Hawker presence",
              "value": 0.3883495145631068,
              "formatted_value": "38.8%",
              "unit": "%"
            },
            {
              "key": "cafe_count_ratio",
              "label": "Cafe presence",
              "value": 0.009708737864077669,
              "formatted_value": "1.0%",
              "unit": "%"
            }
          ],
          "criteria_snapshot": "chinese_count_ratio=0.029; indian_count_ratio=0.019; hawker_stall_count_ratio=0.388; cafe_count_ratio=0.010",
          "kmeans_cluster": 0,
          "cluster_label": "Mainstream Urban / Heartland",
          "cluster_description": "supports stronger everyday demand, denser competition, and a more mass-market, affordable environment.",
          "cluster_assignment_method": "fit",
          "total_footfall": 21356172,
          "income_mix": {
            "low": 0.207,
            "mid": 0.42,
            "high": 0.374
          },
          "competitor_count": 206,
          "rent_proxy_psm": 131.97,
          "primary_demographic": "Mid-Age Adults",
          "primary_demographic_share": 0.304,
          "recommendation_summary": "This area is shortlisted for a local cuisine / traditional favorites and belongs to the Mainstream Urban / Heartland cluster, which supports stronger everyday demand, denser competition, and a more mass-market, affordable environment."
        },
        {
          "rank": 4,
          "planning_area": "JURONG WEST",
          "primary_metric": "hawker_stall_count_ratio",
          "primary_value": 0.387,
          "primary_metric_display": {
            "key": "hawker_stall_count_ratio",
            "label": "Hawker presence",
            "value": 0.3870967741935484,
            "formatted_value": "38.7%",
            "unit": "%"
          },
          "criteria_used": [
            "chinese_count_ratio",
            "indian_count_ratio",
            "hawker_stall_count_ratio",
            "cafe_count_ratio"
          ],
          "criteria_display": [
            {
              "key": "chinese_count_ratio",
              "label": "Chinese cuisine presence",
              "value": 0.053763440860215055,
              "formatted_value": "5.4%",
              "unit": "%"
            },
            {
              "key": "indian_count_ratio",
              "label": "Indian cuisine presence",
              "value": 0.005376344086021506,
              "formatted_value": "0.5%",
              "unit": "%"
            },
            {
              "key": "hawker_stall_count_ratio",
              "label": "Hawker presence",
              "value": 0.3870967741935484,
              "formatted_value": "38.7%",
              "unit": "%"
            },
            {
              "key": "cafe_count_ratio",
              "label": "Cafe presence",
              "value": 0.0,
              "formatted_value": "0.0%",
              "unit": "%"
            }
          ],
          "criteria_snapshot": "chinese_count_ratio=0.054; indian_count_ratio=0.005; hawker_stall_count_ratio=0.387; cafe_count_ratio=0.000",
          "kmeans_cluster": 0,
          "cluster_label": "Mainstream Urban / Heartland",
          "cluster_description": "supports stronger everyday demand, denser competition, and a more mass-market, affordable environment.",
          "cluster_assignment_method": "fit",
          "total_footfall": 18176818,
          "income_mix": {
            "low": 0.192,
            "mid": 0.395,
            "high": 0.413
          },
          "competitor_count": 186,
          "rent_proxy_psm": 154.04,
          "primary_demographic": "Mid-Age Adults",
          "primary_demographic_share": 0.313,
          "recommendation_summary": "This area is shortlisted for a local cuisine / traditional favorites and belongs to the Mainstream Urban / Heartland cluster, which supports stronger everyday demand, denser competition, and a more mass-market, affordable environment."
        },
        {
          "rank": 5,
          "planning_area": "KALLANG",
          "primary_metric": "hawker_stall_count_ratio",
          "primary_value": 0.334,
          "primary_metric_display": {
            "key": "hawker_stall_count_ratio",
            "label": "Hawker presence",
            "value": 0.334070796460177,
            "formatted_value": "33.4%",
            "unit": "%"
          },
          "criteria_used": [
            "chinese_count_ratio",
            "indian_count_ratio",
            "hawker_stall_count_ratio",
            "cafe_count_ratio"
          ],
          "criteria_display": [
            {
              "key": "chinese_count_ratio",
              "label": "Chinese cuisine presence",
              "value": 0.08185840707964602,
              "formatted_value": "8.2%",
              "unit": "%"
            },
            {
              "key": "indian_count_ratio",
              "label": "Indian cuisine presence",
              "value": 0.01991150442477876,
              "formatted_value": "2.0%",
              "unit": "%"
            },
            {
              "key": "hawker_stall_count_ratio",
              "label": "Hawker presence",
              "value": 0.334070796460177,
              "formatted_value": "33.4%",
              "unit": "%"
            },
            {
              "key": "cafe_count_ratio",
              "label": "Cafe presence",
              "value": 0.030973451327433628,
              "formatted_value": "3.1%",
              "unit": "%"
            }
          ],
          "criteria_snapshot": "chinese_count_ratio=0.082; indian_count_ratio=0.020; hawker_stall_count_ratio=0.334; cafe_count_ratio=0.031",
          "kmeans_cluster": 0,
          "cluster_label": "Mainstream Urban / Heartland",
          "cluster_description": "supports stronger everyday demand, denser competition, and a more mass-market, affordable environment.",
          "cluster_assignment_method": "fit",
          "total_footfall": 7519794,
          "income_mix": {
            "low": 0.275,
            "mid": 0.289,
            "high": 0.436
          },
          "competitor_count": 452,
          "rent_proxy_psm": 99.84,
          "primary_demographic": "Mid-Age Adults",
          "primary_demographic_share": 0.302,
          "recommendation_summary": "This area is shortlisted for a local cuisine / traditional favorites and belongs to the Mainstream Urban / Heartland cluster, which supports stronger everyday demand, denser competition, and a more mass-market, affordable environment."
        }
      ]
    },
    "fast_food_grab_go": {
      "description": "Fast-food / grab-and-go concept",
      "primary_metric": "log_footfall",
      "criteria_used": [
        "log_footfall",
        "weekday_ratio",
        "fast_food_count_ratio",
        "teens_youth_ratio",
        "mean_price_mid"
      ],
      "areas": [
        {
          "rank": 1,
          "planning_area": "WOODLANDS",
          "primary_metric": "log_footfall",
          "primary_value": 16.877,
          "primary_metric_display": {
            "key": "log_footfall",
            "label": "Total footfall",
            "value": 21356172,
            "formatted_value": "21,356,172",
            "unit": "visits"
          },
          "criteria_used": [
            "log_footfall",
            "weekday_ratio",
            "fast_food_count_ratio",
            "teens_youth_ratio",
            "mean_price_mid"
          ],
          "criteria_display": [
            {
              "key": "log_footfall",
              "label": "Total footfall",
              "value": 21356172,
              "formatted_value": "21,356,172",
              "unit": "visits"
            },
            {
              "key": "weekday_ratio",
              "label": "Weekday activity share",
              "value": 0.7008934934594083,
              "formatted_value": "70.1%",
              "unit": "%"
            },
            {
              "key": "fast_food_count_ratio",
              "label": "Fast-food presence",
              "value": 0.038834951456310676,
              "formatted_value": "3.9%",
              "unit": "%"
            },
            {
              "key": "teens_youth_ratio",
              "label": "Teens and youth presence",
              "value": 0.15109943950143065,
              "formatted_value": "15.1%",
              "unit": "%"
            },
            {
              "key": "mean_price_mid",
              "label": "Typical price level",
              "value": 9.172185430463577,
              "formatted_value": "9.17",
              "unit": "SGD"
            }
          ],
          "criteria_snapshot": "log_footfall=16.877; weekday_ratio=0.701; fast_food_count_ratio=0.039; teens_youth_ratio=0.151; mean_price_mid=9.172",
          "kmeans_cluster": 0,
          "cluster_label": "Mainstream Urban / Heartland",
          "cluster_description": "supports stronger everyday demand, denser competition, and a more mass-market, affordable environment.",
          "cluster_assignment_method": "fit",
          "total_footfall": 21356172,
          "income_mix": {
            "low": 0.207,
            "mid": 0.42,
            "high": 0.374
          },
          "competitor_count": 206,
          "rent_proxy_psm": 131.97,
          "primary_demographic": "Mid-Age Adults",
          "primary_demographic_share": 0.304,
          "recommendation_summary": "This area is shortlisted for a fast-food / grab-and-go concept and belongs to the Mainstream Urban / Heartland cluster, which supports stronger everyday demand, denser competition, and a more mass-market, affordable environment."
        },
        {
          "rank": 2,
          "planning_area": "TAMPINES",
          "primary_metric": "log_footfall",
          "primary_value": 16.794,
          "primary_metric_display": {
            "key": "log_footfall",
            "label": "Total footfall",
            "value": 19665357,
            "formatted_value": "19,665,357",
            "unit": "visits"
          },
          "criteria_used": [
            "log_footfall",
            "weekday_ratio",
            "fast_food_count_ratio",
            "teens_youth_ratio",
            "mean_price_mid"
          ],
          "criteria_display": [
            {
              "key": "log_footfall",
              "label": "Total footfall",
              "value": 19665357,
              "formatted_value": "19,665,357",
              "unit": "visits"
            },
            {
              "key": "weekday_ratio",
              "label": "Weekday activity share",
              "value": 0.7199796576283868,
              "formatted_value": "72.0%",
              "unit": "%"
            },
            {
              "key": "fast_food_count_ratio",
              "label": "Fast-food presence",
              "value": 0.013100436681222707,
              "formatted_value": "1.3%",
              "unit": "%"
            },
            {
              "key": "teens_youth_ratio",
              "label": "Teens and youth presence",
              "value": 0.11879207539911521,
              "formatted_value": "11.9%",
              "unit": "%"
            },
            {
              "key": "mean_price_mid",
              "label": "Typical price level",
              "value": 13.105421686746988,
              "formatted_value": "13.11",
              "unit": "SGD"
            }
          ],
          "criteria_snapshot": "log_footfall=16.794; weekday_ratio=0.720; fast_food_count_ratio=0.013; teens_youth_ratio=0.119; mean_price_mid=13.105",
          "kmeans_cluster": 0,
          "cluster_label": "Mainstream Urban / Heartland",
          "cluster_description": "supports stronger everyday demand, denser competition, and a more mass-market, affordable environment.",
          "cluster_assignment_method": "fit",
          "total_footfall": 19665357,
          "income_mix": {
            "low": 0.188,
            "mid": 0.35,
            "high": 0.462
          },
          "competitor_count": 229,
          "rent_proxy_psm": 111.17,
          "primary_demographic": "Mid-Age Adults",
          "primary_demographic_share": 0.272,
          "recommendation_summary": "This area is shortlisted for a fast-food / grab-and-go concept and belongs to the Mainstream Urban / Heartland cluster, which supports stronger everyday demand, denser competition, and a more mass-market, affordable environment."
        },
        {
          "rank": 3,
          "planning_area": "JURONG WEST",
          "primary_metric": "log_footfall",
          "primary_value": 16.716,
          "primary_metric_display": {
            "key": "log_footfall",
            "label": "Total footfall",
            "value": 18176818,
            "formatted_value": "18,176,818",
            "unit": "visits"
          },
          "criteria_used": [
            "log_footfall",
            "weekday_ratio",
            "fast_food_count_ratio",
            "teens_youth_ratio",
            "mean_price_mid"
          ],
          "criteria_display": [
            {
              "key": "log_footfall",
              "label": "Total footfall",
              "value": 18176818,
              "formatted_value": "18,176,818",
              "unit": "visits"
            },
            {
              "key": "weekday_ratio",
              "label": "Weekday activity share",
              "value": 0.7089287024824698,
              "formatted_value": "70.9%",
              "unit": "%"
            },
            {
              "key": "fast_food_count_ratio",
              "label": "Fast-food presence",
              "value": 0.03225806451612903,
              "formatted_value": "3.2%",
              "unit": "%"
            },
            {
              "key": "teens_youth_ratio",
              "label": "Teens and youth presence",
              "value": 0.12751703399185413,
              "formatted_value": "12.8%",
              "unit": "%"
            },
            {
              "key": "mean_price_mid",
              "label": "Typical price level",
              "value": 10.71439393939394,
              "formatted_value": "10.71",
              "unit": "SGD"
            }
          ],
          "criteria_snapshot": "log_footfall=16.716; weekday_ratio=0.709; fast_food_count_ratio=0.032; teens_youth_ratio=0.128; mean_price_mid=10.714",
          "kmeans_cluster": 0,
          "cluster_label": "Mainstream Urban / Heartland",
          "cluster_description": "supports stronger everyday demand, denser competition, and a more mass-market, affordable environment.",
          "cluster_assignment_method": "fit",
          "total_footfall": 18176818,
          "income_mix": {
            "low": 0.192,
            "mid": 0.395,
            "high": 0.413
          },
          "competitor_count": 186,
          "rent_proxy_psm": 154.04,
          "primary_demographic": "Mid-Age Adults",
          "primary_demographic_share": 0.313,
          "recommendation_summary": "This area is shortlisted for a fast-food / grab-and-go concept and belongs to the Mainstream Urban / Heartland cluster, which supports stronger everyday demand, denser competition, and a more mass-market, affordable environment."
        },
        {
          "rank": 4,
          "planning_area": "DOWNTOWN CORE",
          "primary_metric": "log_footfall",
          "primary_value": 16.571,
          "primary_metric_display": {
            "key": "log_footfall",
            "label": "Total footfall",
            "value": 15722045,
            "formatted_value": "15,722,045",
            "unit": "visits"
          },
          "criteria_used": [
            "log_footfall",
            "weekday_ratio",
            "fast_food_count_ratio",
            "teens_youth_ratio",
            "mean_price_mid"
          ],
          "criteria_display": [
            {
              "key": "log_footfall",
              "label": "Total footfall",
              "value": 15722045,
              "formatted_value": "15,722,045",
              "unit": "visits"
            },
            {
              "key": "weekday_ratio",
              "label": "Weekday activity share",
              "value": 0.7223172303602998,
              "formatted_value": "72.2%",
              "unit": "%"
            },
            {
              "key": "fast_food_count_ratio",
              "label": "Fast-food presence",
              "value": 0.009210526315789473,
              "formatted_value": "0.9%",
              "unit": "%"
            },
            {
              "key": "teens_youth_ratio",
              "label": "Teens and youth presence",
              "value": 0.06229508196721312,
              "formatted_value": "6.2%",
              "unit": "%"
            },
            {
              "key": "mean_price_mid",
              "label": "Typical price level",
              "value": 33.6,
              "formatted_value": "33.60",
              "unit": "SGD"
            }
          ],
          "criteria_snapshot": "log_footfall=16.571; weekday_ratio=0.722; fast_food_count_ratio=0.009; teens_youth_ratio=0.062; mean_price_mid=33.600",
          "kmeans_cluster": 2,
          "cluster_label": "Premium Central / Lifestyle",
          "cluster_description": "supports higher price points, stronger ratings, and greater category diversity.",
          "cluster_assignment_method": "fit",
          "total_footfall": 15722045,
          "income_mix": {
            "low": 0.073,
            "mid": 0.187,
            "high": 0.74
          },
          "competitor_count": 760,
          "rent_proxy_psm": 211.15,
          "primary_demographic": "Mid-Age Adults",
          "primary_demographic_share": 0.407,
          "recommendation_summary": "This area is shortlisted for a fast-food / grab-and-go concept and belongs to the Premium Central / Lifestyle cluster, which supports higher price points, stronger ratings, and greater category diversity."
        },
        {
          "rank": 5,
          "planning_area": "TOA PAYOH",
          "primary_metric": "log_footfall",
          "primary_value": 16.393,
          "primary_metric_display": {
            "key": "log_footfall",
            "label": "Total footfall",
            "value": 13163275,
            "formatted_value": "13,163,275",
            "unit": "visits"
          },
          "criteria_used": [
            "log_footfall",
            "weekday_ratio",
            "fast_food_count_ratio",
            "teens_youth_ratio",
            "mean_price_mid"
          ],
          "criteria_display": [
            {
              "key": "log_footfall",
              "label": "Total footfall",
              "value": 13163275,
              "formatted_value": "13,163,275",
              "unit": "visits"
            },
            {
              "key": "weekday_ratio",
              "label": "Weekday activity share",
              "value": 0.719194881213072,
              "formatted_value": "71.9%",
              "unit": "%"
            },
            {
              "key": "fast_food_count_ratio",
              "label": "Fast-food presence",
              "value": 0.04918032786885246,
              "formatted_value": "4.9%",
              "unit": "%"
            },
            {
              "key": "teens_youth_ratio",
              "label": "Teens and youth presence",
              "value": 0.09562863938325268,
              "formatted_value": "9.6%",
              "unit": "%"
            },
            {
              "key": "mean_price_mid",
              "label": "Typical price level",
              "value": 10.671128608923883,
              "formatted_value": "10.67",
              "unit": "SGD"
            }
          ],
          "criteria_snapshot": "log_footfall=16.393; weekday_ratio=0.719; fast_food_count_ratio=0.049; teens_youth_ratio=0.096; mean_price_mid=10.671",
          "kmeans_cluster": 0,
          "cluster_label": "Mainstream Urban / Heartland",
          "cluster_description": "supports stronger everyday demand, denser competition, and a more mass-market, affordable environment.",
          "cluster_assignment_method": "fit",
          "total_footfall": 13163275,
          "income_mix": {
            "low": 0.251,
            "mid": 0.322,
            "high": 0.427
          },
          "competitor_count": 488,
          "rent_proxy_psm": 115.66,
          "primary_demographic": "Mid-Age Adults",
          "primary_demographic_share": 0.286,
          "recommendation_summary": "This area is shortlisted for a fast-food / grab-and-go concept and belongs to the Mainstream Urban / Heartland cluster, which supports stronger everyday demand, denser competition, and a more mass-market, affordable environment."
        }
      ]
    }
  }
}